[{"structural_material": "bone", "height": 5, "py/object": "components.body.Body", "outer_material_uid": null, "bodypart_tree": {"nodes": [{"children_nodes": [{"children_nodes": [], "body_part_uid": "humanoid_heart", "py/object": "components.body.BodypartTreeNode", "connection_type": 2, "name": "heart"}, {"children_nodes": [], "body_part_uid": "humanoid_lungs", "py/object": "components.body.BodypartTreeNode", "connection_type": 2, "name": "lungs"}, {"children_nodes": [{"children_nodes": [], "body_part_uid": "humanoid_eye", "py/object": "components.body.BodypartTreeNode", "connection_type": 1, "name": "left eye"}, {"children_nodes": [], "body_part_uid": "humanoid_eye", "py/object": "components.body.BodypartTreeNode", "connection_type": 1, "name": "right eye"}, {"children_nodes": [], "body_part_uid": "humanoid_ear", "py/object": "components.body.BodypartTreeNode", "connection_type": 1, "name": "left ear"}, {"children_nodes": [], "body_part_uid": "humanoid_ear", "py/object": "components.body.BodypartTreeNode", "connection_type": 1, "name": "right ear"}, {"children_nodes": [], "body_part_uid": "humanoid_mouth", "py/object": "components.body.BodypartTreeNode", "connection_type": 1, "name": "mouth"}, {"children_nodes": [], "body_part_uid": "humanoid_brain", "py/object": "components.body.BodypartTreeNode", "connection_type": 2, "name": "brain"}], "body_part_uid": "humanoid_head", "py/object": "components.body.BodypartTreeNode", "connection_type": 1, "name": "head"}, {"children_nodes": [{"children_nodes": [], "body_part_uid": "humanoid_hand", "py/object": "components.body.BodypartTreeNode", "connection_type": 1, "name": "left hand"}], "body_part_uid": "humanoid_arm", "py/object": "components.body.BodypartTreeNode", "connection_type": 1, "name": "left arm"}, {"children_nodes": [{"children_nodes": [], "body_part_uid": "humanoid_hand", "py/object": "components.body.BodypartTreeNode", "connection_type": 1, "name": "right hand"}], "body_part_uid": "humanoid_arm", "py/object": "components.body.BodypartTreeNode", "connection_type": 1, "name": "right arm"}, {"children_nodes": [{"children_nodes": [], "body_part_uid": "humanoid_foot", "py/object": "components.body.BodypartTreeNode", "connection_type": 1, "name": "left foot"}], "body_part_uid": "humanoid_leg", "py/object": "components.body.BodypartTreeNode", "connection_type": 1, "name": "left leg"}, {"children_nodes": [{"children_nodes": [], "body_part_uid": "humanoid_foot", "py/object": "components.body.BodypartTreeNode", "connection_type": 1, "name": "right foot"}], "body_part_uid": "humanoid_leg", "py/object": "components.body.BodypartTreeNode", "connection_type": 1, "name": "right leg"}], "body_part_uid": "humanoid_torso", "py/object": "components.body.BodypartTreeNode", "connection_type": 0, "name": "torso"}, {"py/id": 6}, {"py/id": 8}, {"py/id": 10}, {"py/id": 12}, {"py/id": 14}, {"py/id": 16}, {"py/id": 18}, {"py/id": 20}, {"py/id": 22}, {"py/id": 24}, {"py/id": 26}, {"py/id": 28}, {"py/id": 30}, {"py/id": 32}, {"py/id": 34}, {"py/id": 36}, {"py/id": 38}], "py/object": "components.body.BodypartTree"}, "structural_material_uid": null, "inner_material": "flesh", "weight": 150, "inner_material_uid": null, "uid": "humanoid", "name": "Humanoid", "outer_material": "skin", "blood_uid": null, "blood_type": "humanoid_blood"}]